petersburgedu_wrap/__init__.py
petersburgedu_wrap/client.py
petersburgedu_wrap/errors/__init__.py
petersburgedu_wrap/errors/invalid_login_or_password_exc.py
petersburgedu_wrap/types/__init__.py
petersburgedu_wrap/types/action_payload.py
petersburgedu_wrap/types/child.py
petersburgedu_wrap/types/education.py
petersburgedu_wrap/types/estimate.py
petersburgedu_wrap/types/identity.py
petersburgedu_wrap/types/lesson_entry.py
petersburgedu_wrap/types/mark_entry.py
petersburgedu_wrap/types/subject.py
petersburgedu_wrap/types/task.py
petersburgedu_wrap/types/teacher.py
petersburgedu_wrap/utils/__init__.py
petersburgedu_wrap/utils/endpoints.py
petersburgedu_wrap/utils/request_parameters.py
petersburgedu_wrap-0.0.1.dist-info/LICENSE
petersburgedu_wrap-0.0.1.dist-info/METADATA
petersburgedu_wrap-0.0.1.dist-info/WHEEL
petersburgedu_wrap-0.0.1.dist-info/top_level.txt
petersburgedu_wrap-0.0.1.dist-info/RECORD
