Metadata-Version: 2.1
Name: petersburgedu-wrap
Version: 0.0.1
Summary: This is module for work with petersburgedu website API
Home-page: https://github.com/Zeusina/petersbugredu-wrap-python
Author: zeusina
Author-email: kachusov_k@outlook.com
Project-URL: Source, https://github.com/Zeusina/petersbugredu-wrap-python
Keywords: api python petersburgedu
Classifier: Programming Language :: Python :: 3.10
Classifier: Operating System :: OS Independent
Requires-Python: >=3.8
License-File: LICENSE
Requires-Dist: requests (>=2.25.1)
